{"v":"5.9.0","fr":25,"ip":0,"op":44,"w":600,"h":600,"nm":"1 Like","ddd":0,"assets":[{"id":"comp_0","nm":"Pre-comp 1","fr":25,"layers":[{"ddd":0,"ind":1,"ty":0,"nm":"Logo - Like","refId":"comp_1","sr":1,"ks":{"o":{"a":0,"k":100,"ix":11},"r":{"a":0,"k":0,"ix":10},"p":{"a":0,"k":[500,500,0],"ix":2,"l":2},"a":{"a":0,"k":[525,525,0],"ix":1,"l":2},"s":{"a":0,"k":[100,100,100],"ix":6,"l":2}},"ao":0,"w":1050,"h":1050,"ip":0,"op":15000,"st":0,"bm":0},{"ddd":0,"ind":2,"ty":4,"nm":"Face","sr":1,"ks":{"o":{"a":0,"k":100,"ix":11},"r":{"a":0,"k":0,"ix":10},"p":{"a":0,"k":[500,500,0],"ix":2,"l":2},"a":{"a":0,"k":[500.25,500.25,0],"ix":1,"l":2},"s":{"a":0,"k":[100,100,100],"ix":6,"l":2}},"ao":0,"shapes":[{"ty":"gr","it":[{"ind":0,"ty":"sh","ix":1,"ks":{"a":0,"k":{"i":[[132.606,0],[93.767,-93.769],[0,-132.608],[-93.769,-93.77],[-132.608,0],[-93.769,93.761],[0,132.607],[93.762,93.768]],"o":[[-132.608,0],[-93.769,93.768],[0,132.607],[93.767,93.761],[132.606,0],[93.762,-93.77],[0,-132.608],[-93.769,-93.769]],"v":[[0,-500],[-353.553,-353.553],[-500,0],[-353.553,353.557],[0,500],[353.556,353.557],[500,0],[353.556,-353.553]],"c":true},"ix":2},"nm":"Path 1","mn":"ADBE Vector Shape - Group","hd":false},{"ty":"gf","o":{"a":0,"k":100,"ix":10},"r":1,"bm":0,"g":{"p":3,"k":{"a":0,"k":[0,0.094,0.678,0.996,0.474,0.049,0.537,0.937,1,0.004,0.396,0.878],"ix":9}},"s":{"a":0,"k":[466.539,-264.001],"ix":5},"e":{"a":0,"k":[-456.059,323.695],"ix":6},"t":1,"nm":"Gradient Fill 1","mn":"ADBE Vector Graphic - G-Fill","hd":false},{"ty":"tr","p":{"a":0,"k":[500.25,500.25],"ix":2},"a":{"a":0,"k":[0,0],"ix":1},"s":{"a":0,"k":[100,100],"ix":3},"r":{"a":0,"k":0,"ix":6},"o":{"a":0,"k":100,"ix":7},"sk":{"a":0,"k":0,"ix":4},"sa":{"a":0,"k":0,"ix":5},"nm":"Transform"}],"nm":"Group 1","np":2,"cix":2,"bm":0,"ix":1,"mn":"ADBE Vector Group","hd":false}],"ip":0,"op":29336,"st":0,"bm":0}]},{"id":"comp_1","nm":"Logo - Like","fr":25,"layers":[{"ddd":0,"ind":1,"ty":3,"nm":"Controller","sr":1,"ks":{"o":{"a":0,"k":0,"ix":11},"r":{"a":0,"k":0,"ix":10},"p":{"a":0,"k":[525,525,0],"ix":2,"l":2},"a":{"a":0,"k":[50,50,0],"ix":1,"l":2},"s":{"a":0,"k":[100,100,100],"ix":6,"l":2}},"ao":0,"ef":[{"ty":5,"nm":"Original Emoji Color","np":3,"mn":"ADBE Checkbox Control","ix":1,"en":1,"ef":[{"ty":7,"nm":"Checkbox","mn":"ADBE Checkbox Control-0001","ix":1,"v":{"a":0,"k":0,"ix":1}}]},{"ty":5,"nm":"Original Emoji / Custom Logo","np":3,"mn":"ADBE Checkbox Control","ix":2,"en":1,"ef":[{"ty":7,"nm":"Checkbox","mn":"ADBE Checkbox Control-0001","ix":1,"v":{"a":0,"k":1,"ix":1}}]}],"ip":0,"op":15000,"st":0,"bm":0},{"ddd":0,"ind":2,"ty":3,"nm":"Logo Color","sr":1,"ks":{"o":{"a":0,"k":100,"ix":11,"x":"var $bm_rt;\n$bm_rt = $bm_mul(thisComp.layer('Controller').effect('Original Emoji Color')('ADBE Checkbox Control-0001'), 100);"},"r":{"a":0,"k":0,"ix":10},"p":{"a":0,"k":[525,525,0],"ix":2,"l":2},"a":{"a":0,"k":[525,525,0],"ix":1,"l":2},"s":{"a":0,"k":[100,100,100],"ix":6,"l":2}},"ao":0,"ef":[{"ty":21,"nm":"Fill","np":9,"mn":"ADBE Fill","ix":1,"en":1,"ef":[{"ty":10,"nm":"Fill Mask","mn":"ADBE Fill-0001","ix":1,"v":{"a":0,"k":0,"ix":1}},{"ty":7,"nm":"All Masks","mn":"ADBE Fill-0007","ix":2,"v":{"a":0,"k":0,"ix":2}},{"ty":2,"nm":"Color","mn":"ADBE Fill-0002","ix":3,"v":{"a":0,"k":[1,1,1,1],"ix":3,"x":"var $bm_rt;\nvar temp;\ntemp = thisComp.layer('Controller').effect('Original Emoji Color')('ADBE Checkbox Control-0001');\n$bm_rt = [\n    temp,\n    temp,\n    temp,\n    temp\n];"}},{"ty":7,"nm":"Invert","mn":"ADBE Fill-0006","ix":4,"v":{"a":0,"k":0,"ix":4}},{"ty":0,"nm":"Horizontal Feather","mn":"ADBE Fill-0003","ix":5,"v":{"a":0,"k":0,"ix":5}},{"ty":0,"nm":"Vertical Feather","mn":"ADBE Fill-0004","ix":6,"v":{"a":0,"k":0,"ix":6}},{"ty":0,"nm":"Opacity","mn":"ADBE Fill-0005","ix":7,"v":{"a":0,"k":1,"ix":7}}]}],"ip":0,"op":15000,"st":0,"bm":0},{"ddd":0,"ind":3,"ty":0,"nm":"Hand","refId":"comp_2","sr":1,"ks":{"o":{"a":0,"k":100,"ix":11,"x":"var $bm_rt;\n$bm_rt = $bm_mul(thisComp.layer('Controller').effect('Original Emoji / Custom Logo')('ADBE Checkbox Control-0001'), 100);"},"r":{"a":0,"k":0,"ix":10},"p":{"a":0,"k":[500,500,0],"ix":2,"l":2},"a":{"a":0,"k":[500,500,0],"ix":1,"l":2},"s":{"a":0,"k":[100,100,100],"ix":6,"l":2}},"ao":0,"w":1000,"h":1000,"ip":0,"op":15000,"st":0,"bm":0}]},{"id":"comp_2","nm":"Hand","fr":25,"layers":[{"ddd":0,"ind":1,"ty":4,"nm":"Hand","sr":1,"ks":{"o":{"a":0,"k":100,"ix":11},"r":{"a":1,"k":[{"i":{"x":[0.667],"y":[1]},"o":{"x":[0.333],"y":[0]},"t":1,"s":[0]},{"i":{"x":[0.667],"y":[1]},"o":{"x":[0.333],"y":[0]},"t":4,"s":[6]},{"i":{"x":[0.667],"y":[1]},"o":{"x":[0.333],"y":[0]},"t":6,"s":[6]},{"i":{"x":[0.667],"y":[1]},"o":{"x":[0.333],"y":[0]},"t":20,"s":[-6]},{"i":{"x":[0.667],"y":[1]},"o":{"x":[0.333],"y":[0]},"t":29,"s":[6]},{"i":{"x":[0.667],"y":[1]},"o":{"x":[0.333],"y":[0]},"t":35,"s":[-3]},{"i":{"x":[0.667],"y":[1]},"o":{"x":[0.333],"y":[0]},"t":38,"s":[0]},{"i":{"x":[0.667],"y":[1]},"o":{"x":[0.333],"y":[0]},"t":45,"s":[0]},{"t":50,"s":[0]}],"ix":10,"x":"var $bm_rt;\n$bm_rt = loopOut('cycle', 0);"},"p":{"a":1,"k":[{"i":{"x":0.667,"y":1},"o":{"x":0.333,"y":0},"t":0,"s":[285.04,563.538,0],"to":[4,0,0],"ti":[-4,0,0]},{"i":{"x":0.667,"y":0.667},"o":{"x":0.333,"y":0.333},"t":1,"s":[309.04,563.538,0],"to":[0,0,0],"ti":[0,0,0]},{"i":{"x":0.667,"y":1},"o":{"x":0.333,"y":0},"t":6,"s":[309.04,563.538,0],"to":[-10,5,0],"ti":[3.5,0,0]},{"i":{"x":0.667,"y":1},"o":{"x":0.333,"y":0},"t":20,"s":[249.04,593.537,0],"to":[-3.5,0,0],"ti":[-6,5,0]},{"i":{"x":0.667,"y":1},"o":{"x":0.333,"y":0},"t":29,"s":[288.04,563.538,0],"to":[6,-5,0],"ti":[0.5,0,0]},{"i":{"x":0.667,"y":0.667},"o":{"x":0.333,"y":0.333},"t":45,"s":[285.04,563.538,0],"to":[0,0,0],"ti":[0,0,0]},{"t":50,"s":[285.04,563.538,0]}],"ix":2,"l":2,"x":"var $bm_rt;\n$bm_rt = loopOut('cycle', 0);"},"a":{"a":0,"k":[62.75,156.5,0],"ix":1,"l":2},"s":{"a":1,"k":[{"i":{"x":[0.667,0.667,0.667],"y":[1,1,1]},"o":{"x":[0.333,0.333,0.333],"y":[0,0,0]},"t":0,"s":[100,100,100]},{"i":{"x":[0.667,0.667,0.667],"y":[1,1,1]},"o":{"x":[0.333,0.333,0.333],"y":[0,0,0]},"t":1,"s":[85,85,100]},{"i":{"x":[0.667,0.667,0.667],"y":[1,1,1]},"o":{"x":[0.333,0.333,0.333],"y":[0,0,0]},"t":4,"s":[85,85,100]},{"i":{"x":[0.667,0.667,0.667],"y":[1,1,1]},"o":{"x":[0.333,0.333,0.333],"y":[0,0,0]},"t":20,"s":[110,110,100]},{"i":{"x":[0.667,0.667,0.667],"y":[1,1,1]},"o":{"x":[0.333,0.333,0.333],"y":[0,0,0]},"t":29,"s":[100,100,100]},{"i":{"x":[0.667,0.667,0.667],"y":[1,1,1]},"o":{"x":[0.333,0.333,0.333],"y":[0,0,0]},"t":45,"s":[100,100,100]},{"t":50,"s":[100,100,100]}],"ix":6,"l":2,"x":"var $bm_rt;\n$bm_rt = loopOut('cycle', 0);"}},"ao":0,"shapes":[{"ty":"gr","it":[{"ind":0,"ty":"sh","ix":1,"ks":{"a":0,"k":{"i":[[-9.946,0],[0,0],[-7.032,-7.033],[0,-9.946],[0,0],[7.033,-7.038],[9.946,0],[0,0],[7.032,7.031],[0,9.943],[0,0],[-7.033,7.032]],"o":[[0,0],[9.946,0],[7.033,7.032],[0,0],[0,9.943],[-7.032,7.031],[0,0],[-9.946,0],[-7.033,-7.038],[0,0],[0,-9.946],[7.032,-7.033]],"v":[[-25,-156.25],[25,-156.25],[51.516,-145.266],[62.5,-118.75],[62.5,118.75],[51.516,145.269],[25,156.25],[-25,156.25],[-51.516,145.269],[-62.5,118.75],[-62.5,-118.75],[-51.516,-145.266]],"c":true},"ix":2},"nm":"Path 1","mn":"ADBE Vector Shape - Group","hd":false},{"ty":"fl","c":{"a":0,"k":[1,1,1,1],"ix":4},"o":{"a":0,"k":100,"ix":5},"r":1,"bm":0,"nm":"Fill 1","mn":"ADBE Vector Graphic - Fill","hd":false},{"ty":"tr","p":{"a":0,"k":[62.75,156.5],"ix":2},"a":{"a":0,"k":[0,0],"ix":1},"s":{"a":0,"k":[100,100],"ix":3},"r":{"a":0,"k":0,"ix":6},"o":{"a":0,"k":100,"ix":7},"sk":{"a":0,"k":0,"ix":4},"sa":{"a":0,"k":0,"ix":5},"nm":"Transform"}],"nm":"Group 1","np":2,"cix":2,"bm":0,"ix":1,"mn":"ADBE Vector Group","hd":false}],"ip":0,"op":24613,"st":0,"bm":0},{"ddd":0,"ind":2,"ty":4,"nm":"Thumb","sr":1,"ks":{"o":{"a":0,"k":100,"ix":11},"r":{"a":1,"k":[{"i":{"x":[0.667],"y":[1]},"o":{"x":[0.333],"y":[0]},"t":1,"s":[0]},{"i":{"x":[0.667],"y":[1]},"o":{"x":[0.333],"y":[0]},"t":4,"s":[9]},{"i":{"x":[0.667],"y":[1]},"o":{"x":[0.333],"y":[0]},"t":6,"s":[9]},{"i":{"x":[0.667],"y":[1]},"o":{"x":[0.333],"y":[0]},"t":20,"s":[-13]},{"i":{"x":[0.667],"y":[1]},"o":{"x":[0.333],"y":[0]},"t":29,"s":[9]},{"i":{"x":[0.667],"y":[1]},"o":{"x":[0.333],"y":[0]},"t":35,"s":[-3]},{"i":{"x":[0.667],"y":[1]},"o":{"x":[0.333],"y":[0]},"t":38,"s":[0]},{"i":{"x":[0.667],"y":[1]},"o":{"x":[0.333],"y":[0]},"t":45,"s":[0]},{"t":50,"s":[0]}],"ix":10,"x":"var $bm_rt;\n$bm_rt = loopOut('cycle', 0);"},"p":{"a":1,"k":[{"i":{"x":0.667,"y":1},"o":{"x":0.333,"y":0},"t":0,"s":[410.085,717.622,0],"to":[0,-6.667,0],"ti":[0,6.667,0]},{"i":{"x":0.667,"y":0.667},"o":{"x":0.333,"y":0.333},"t":1,"s":[410.085,677.622,0],"to":[0,0,0],"ti":[0,0,0]},{"i":{"x":0.667,"y":0.667},"o":{"x":0.333,"y":0.333},"t":5,"s":[410.085,677.622,0],"to":[0,0,0],"ti":[0,0,0]},{"i":{"x":0.667,"y":1},"o":{"x":0.333,"y":0},"t":6,"s":[410.085,677.622,0],"to":[0,7,0],"ti":[0,-6.667,0]},{"i":{"x":0.667,"y":1},"o":{"x":0.333,"y":0},"t":20,"s":[410.085,719.622,0],"to":[0,6.667,0],"ti":[0,0.333,0]},{"i":{"x":0.667,"y":0.667},"o":{"x":0.333,"y":0.333},"t":29,"s":[410.085,717.622,0],"to":[0,0,0],"ti":[0,0,0]},{"i":{"x":0.667,"y":0.667},"o":{"x":0.333,"y":0.333},"t":45,"s":[410.085,717.622,0],"to":[0,0,0],"ti":[0,0,0]},{"t":50,"s":[410.085,717.622,0]}],"ix":2,"l":2,"x":"var $bm_rt;\n$bm_rt = loopOut('cycle', 0);"},"a":{"a":0,"k":[12.717,505.575,0],"ix":1,"l":2},"s":{"a":1,"k":[{"i":{"x":[0.667,0.667,0.667],"y":[1,1,1]},"o":{"x":[0.333,0.333,0.333],"y":[0,0,0]},"t":0,"s":[100,100,100]},{"i":{"x":[0.667,0.667,0.667],"y":[1,1,1]},"o":{"x":[0.333,0.333,0.333],"y":[0,0,0]},"t":1,"s":[85,85,100]},{"i":{"x":[0.667,0.667,0.667],"y":[1,1,1]},"o":{"x":[0.333,0.333,0.333],"y":[0,0,0]},"t":4,"s":[85,85,100]},{"i":{"x":[0.667,0.667,0.667],"y":[1,1,1]},"o":{"x":[0.333,0.333,0.333],"y":[0,0,0]},"t":20,"s":[110,110,100]},{"i":{"x":[0.667,0.667,0.667],"y":[1,1,1]},"o":{"x":[0.333,0.333,0.333],"y":[0,0,0]},"t":29,"s":[100,100,100]},{"i":{"x":[0.667,0.667,0.667],"y":[1,1,1]},"o":{"x":[0.333,0.333,0.333],"y":[0,0,0]},"t":45,"s":[100,100,100]},{"t":50,"s":[100,100,100]}],"ix":6,"l":2,"x":"var $bm_rt;\n$bm_rt = loopOut('cycle', 0);"}},"ao":0,"shapes":[{"ty":"gr","it":[{"ind":0,"ty":"sh","ix":1,"ks":{"a":1,"k":[{"i":{"x":0.667,"y":1},"o":{"x":0.333,"y":0},"t":5,"s":[{"i":[[6.062,-8.938],[0,-26.812],[15.312,-7.563],[2.694,-11.665],[17.501,-4.937],[9,-14.687],[44.5,0],[0,0],[0,28.375],[0,0],[0,53.437],[0,0],[-3.125,2.875],[-20.875,0],[-10.687,-5.125],[0,-35.25],[3.5,-17.562],[-63.249,0.437],[0,-40.75]],"o":[[11,7.687],[0,26.875],[6.256,10.205],[-4.812,21.499],[7.563,12.125],[-11.563,18.438],[0,0],[-61.75,0],[0,0],[0,-76.875],[0,0],[-0.313,-4.062],[5,-4.937],[13.625,0],[36.313,17.312],[0,16.937],[0,0],[66.313,-0.375],[0,16.313]],"v":[[182,21.125],[203.125,63.25],[173.5,108.563],[179.062,142.688],[137.062,185.812],[138,224.562],[71.875,250],[-109.375,250],[-203.125,187.5],[-203.125,41.562],[-111.437,-154.062],[-118.062,-220.625],[-114.437,-237.5],[-74.75,-250],[-41.375,-242.312],[4.375,-145.937],[-25,-60.688],[92.437,-73.125],[201.75,-20.5]],"c":true}]},{"i":{"x":0.667,"y":1},"o":{"x":0.333,"y":0},"t":7,"s":[{"i":[[6.062,-8.938],[0,-26.812],[15.312,-7.563],[2.694,-11.665],[17.501,-4.937],[9,-14.687],[44.5,0],[0,0],[0,28.375],[0,0],[-30.347,90.821],[0,0],[-3.125,2.875],[-20.875,0.118],[-10.268,-11.63],[8.842,-31.224],[3.5,-17.562],[-63.249,0.437],[0,-40.75]],"o":[[11,7.687],[0,26.875],[6.256,10.205],[-4.812,21.499],[7.563,12.125],[-11.563,18.438],[0,0],[-61.75,0],[0,0],[0,-76.875],[0,0],[2.907,-10.288],[5,-4.937],[13.737,-0.077],[25.202,38.571],[-4.615,16.296],[0,0],[66.313,-0.375],[0,16.313]],"v":[[182,21.125],[203.125,63.25],[173.5,108.563],[179.062,142.688],[137.062,185.812],[138,224.562],[71.875,250],[-109.375,250],[-203.125,187.5],[-203.125,41.562],[-97.497,-163.397],[-84.372,-217.675],[-71.673,-237.179],[-28.515,-250.231],[-0.374,-238.152],[2.191,-137.285],[-25,-60.688],[92.437,-73.125],[201.75,-20.5]],"c":true}]},{"i":{"x":0.667,"y":1},"o":{"x":0.333,"y":0},"t":12,"s":[{"i":[[6.062,-8.938],[0,-26.812],[15.312,-7.563],[2.694,-11.665],[17.501,-4.937],[9,-14.687],[44.5,0],[0,0],[0,28.375],[0,0],[0,53.437],[0,0],[-3.125,2.875],[-20.875,0],[-10.687,-5.125],[-3.193,-35.417],[3.5,-17.562],[-63.249,0.437],[0,-40.75]],"o":[[11,7.687],[0,26.875],[6.256,10.205],[-4.812,21.499],[7.563,12.125],[-11.563,18.438],[0,0],[-61.75,0],[0,0],[0,-76.875],[0,0],[-0.313,-4.062],[5,-4.937],[13.625,0],[36.313,17.312],[2.699,29.935],[0,0],[66.313,-0.375],[0,16.313]],"v":[[182,21.125],[203.125,63.25],[173.5,108.563],[179.062,142.688],[137.062,185.812],[138,224.562],[71.875,250],[-109.375,250],[-203.125,187.5],[-203.125,41.562],[-111.437,-154.062],[-118.062,-220.625],[-114.437,-237.5],[-74.75,-250],[-41.375,-242.312],[4.375,-145.937],[-25,-60.688],[92.437,-73.125],[201.75,-20.5]],"c":true}]},{"i":{"x":0.667,"y":1},"o":{"x":0.333,"y":0},"t":45,"s":[{"i":[[6.062,-8.938],[0,-26.812],[15.312,-7.563],[2.694,-11.665],[17.501,-4.937],[9,-14.687],[44.5,0],[0,0],[0,28.375],[0,0],[0,53.437],[0,0],[-3.125,2.875],[-20.875,0],[-10.687,-5.125],[3.881,-38.86],[3.5,-17.562],[-63.249,0.437],[0,-40.75]],"o":[[11,7.687],[0,26.875],[6.256,10.205],[-4.812,21.499],[7.563,12.125],[-11.563,18.438],[0,0],[-61.75,0],[0,0],[0,-76.875],[0,0],[-0.313,-4.062],[5,-4.937],[13.625,0],[36.313,17.312],[-1.683,16.853],[0,0],[66.313,-0.375],[0,16.313]],"v":[[182,21.125],[203.125,63.25],[173.5,108.563],[179.062,142.688],[137.062,185.812],[138,224.562],[71.875,250],[-109.375,250],[-203.125,187.5],[-203.125,41.562],[-111.437,-154.062],[-118.062,-220.625],[-114.437,-237.5],[-74.75,-250],[-41.375,-242.312],[4.375,-145.937],[-25,-60.688],[92.437,-73.125],[201.75,-20.5]],"c":true}]},{"t":50,"s":[{"i":[[6.062,-8.938],[0,-26.812],[15.312,-7.563],[2.694,-11.665],[17.501,-4.937],[9,-14.687],[44.5,0],[0,0],[0,28.375],[0,0],[0,53.437],[0,0],[-3.125,2.875],[-20.875,0],[-10.687,-5.125],[3.881,-38.86],[3.5,-17.562],[-63.249,0.437],[0,-40.75]],"o":[[11,7.687],[0,26.875],[6.256,10.205],[-4.812,21.499],[7.563,12.125],[-11.563,18.438],[0,0],[-61.75,0],[0,0],[0,-76.875],[0,0],[-0.313,-4.062],[5,-4.937],[13.625,0],[36.313,17.312],[-1.683,16.853],[0,0],[66.313,-0.375],[0,16.313]],"v":[[182,21.125],[203.125,63.25],[173.5,108.563],[179.062,142.688],[137.062,185.812],[138,224.562],[71.875,250],[-109.375,250],[-203.125,187.5],[-203.125,41.562],[-111.437,-154.062],[-118.062,-220.625],[-114.437,-237.5],[-74.75,-250],[-41.375,-242.312],[4.375,-145.937],[-25,-60.688],[92.437,-73.125],[201.75,-20.5]],"c":true}]}],"ix":2,"x":"var $bm_rt;\n$bm_rt = valueAtTime($bm_mod(time, key(numKeys).time));"},"nm":"Path 1","mn":"ADBE Vector Shape - Group","hd":false},{"ty":"fl","c":{"a":0,"k":[1,1,1,1],"ix":4},"o":{"a":0,"k":100,"ix":5},"r":1,"bm":0,"nm":"Fill 1","mn":"ADBE Vector Graphic - Fill","hd":false},{"ty":"tr","p":{"a":0,"k":[203.375,250.25],"ix":2},"a":{"a":0,"k":[0,0],"ix":1},"s":{"a":0,"k":[100,100],"ix":3},"r":{"a":0,"k":0,"ix":6},"o":{"a":0,"k":100,"ix":7},"sk":{"a":0,"k":0,"ix":4},"sa":{"a":0,"k":0,"ix":5},"nm":"Transform"}],"nm":"Group 1","np":2,"cix":2,"bm":0,"ix":1,"mn":"ADBE Vector Group","hd":false}],"ip":0,"op":23548,"st":0,"bm":0}]}],"layers":[{"ddd":0,"ind":1,"ty":0,"nm":"Pre-comp 1","refId":"comp_0","sr":1,"ks":{"o":{"a":0,"k":100,"ix":11},"r":{"a":0,"k":0,"ix":10},"p":{"a":0,"k":[300,300,0],"ix":2,"l":2},"a":{"a":0,"k":[500,500,0],"ix":1,"l":2},"s":{"a":1,"k":[{"i":{"x":[0.667,0.667,0.667],"y":[1,1,1]},"o":{"x":[1,1,0.333],"y":[0,0,0]},"t":2,"s":[40,40,100]},{"i":{"x":[0,0,0.667],"y":[1,1,1]},"o":{"x":[0.333,0.333,0.333],"y":[0,0,0]},"t":14.513,"s":[60,60,100]},{"i":{"x":[0,0,0.667],"y":[1,1,1]},"o":{"x":[0.167,0.167,0.167],"y":[0,0,0]},"t":27.025,"s":[40,40,100]},{"t":85.4169921875,"s":[40,40,100]}],"ix":6,"l":2,"x":"var $bm_rt;\n$bm_rt = loopOut('cycle', 0);"}},"ao":0,"w":1000,"h":1000,"ip":0,"op":15000,"st":0,"bm":0}],"markers":[]}